LICENSE
README.md
setup.py
cppasv/__init__.py
cppasv.egg-info/PKG-INFO
cppasv.egg-info/SOURCES.txt
cppasv.egg-info/dependency_links.txt
cppasv.egg-info/top_level.txt