Metadata-Version: 2.1
Name: cppasv
Version: 0.2.0
Summary: Google C++ Benchmarks in Airspeed Velocity
Home-page: https://github.com/flatsurf/cppasv
Author: Julian Rüth
Author-email: julian.rueth@fsfe.org
License: UNKNOWN
Platform: UNKNOWN
Classifier: Programming Language :: Python :: 3
Classifier: License :: OSI Approved :: BSD License
Classifier: Operating System :: OS Independent
Requires-Python: >=3.6
License-File: LICENSE
